Moose/FitUtil.py
Moose/Simulation.py
Moose/__init__.py
Moose/data/C2_swan.db
Moose/data/C2_swan_J300.db
Moose/data/CNBX.db
Moose/data/N2CB.db
Moose/data/N2PlusBX.db
Moose/data/NHAX.db
Moose/data/NOBX.db
Moose/data/OHAX.db
Moose/data/data_sources.txt
moose_spectra-0.2.1.dist-info/METADATA
moose_spectra-0.2.1.dist-info/WHEEL
moose_spectra-0.2.1.dist-info/licenses/LICENSE
moose_spectra-0.2.1.dist-info/RECORD
