Metadata-Version: 2.4
Name: moose-spectra
Version: 0.2.1
Summary: A package to simulate diatomic optical emission spectra relying on line-by-line databases compiled for MassiveOES
Project-URL: Source, https://github.com/AntoineTUE/Moose
Project-URL: Documentation, https://antoinetue.github.io/Moose/
Author-email: Antoine Salden <t.p.w.salden@tue.nl>
License-Expression: MIT
License-File: LICENSE
Classifier: Intended Audience :: Science/Research
Classifier: License :: OSI Approved :: MIT License
Classifier: Operating System :: OS Independent
Classifier: Programming Language :: Python :: 3.9
Classifier: Programming Language :: Python :: 3.10
Classifier: Programming Language :: Python :: 3.11
Classifier: Programming Language :: Python :: 3.12
Classifier: Topic :: Scientific/Engineering
Requires-Python: >=3.9
Requires-Dist: numpy
Requires-Dist: pandas
Requires-Dist: scipy
Provides-Extra: all
Requires-Dist: black; extra == 'all'
Requires-Dist: dask; extra == 'all'
Requires-Dist: ipympl; extra == 'all'
Requires-Dist: ipywidgets; extra == 'all'
Requires-Dist: lmfit; extra == 'all'
Requires-Dist: matplotlib; extra == 'all'
Requires-Dist: mkdocs-gen-files; extra == 'all'
Requires-Dist: mkdocs-git-revision-date-localized-plugin; extra == 'all'
Requires-Dist: mkdocs-jupyter; extra == 'all'
Requires-Dist: mkdocs-literate-nav; extra == 'all'
Requires-Dist: mkdocs-material; extra == 'all'
Requires-Dist: mkdocs-section-index; extra == 'all'
Requires-Dist: mkdocstrings; extra == 'all'
Requires-Dist: mkdocstrings-python; extra == 'all'
Requires-Dist: panel; extra == 'all'
Requires-Dist: plotly; extra == 'all'
Requires-Dist: pygments; extra == 'all'
Provides-Extra: docs
Requires-Dist: black; extra == 'docs'
Requires-Dist: mkdocs-gen-files; extra == 'docs'
Requires-Dist: mkdocs-git-revision-date-localized-plugin; extra == 'docs'
Requires-Dist: mkdocs-jupyter; extra == 'docs'
Requires-Dist: mkdocs-literate-nav; extra == 'docs'
Requires-Dist: mkdocs-material; extra == 'docs'
Requires-Dist: mkdocs-section-index; extra == 'docs'
Requires-Dist: mkdocstrings; extra == 'docs'
Requires-Dist: mkdocstrings-python; extra == 'docs'
Requires-Dist: pygments; extra == 'docs'
Provides-Extra: examples
Requires-Dist: dask; extra == 'examples'
Requires-Dist: ipympl; extra == 'examples'
Requires-Dist: ipywidgets; extra == 'examples'
Requires-Dist: lmfit; extra == 'examples'
Requires-Dist: matplotlib; extra == 'examples'
Requires-Dist: panel; extra == 'examples'
Requires-Dist: plotly; extra == 'examples'
Provides-Extra: fit
Requires-Dist: lmfit; extra == 'fit'
